[
 {
  "id": 1,
  "correct": "The quick brown fox jumps over the lazy dog.",
  "user": "The quick brown fox jump over lazy dog."
 },
 {
  "id": 2,
  "correct": "She is going to the market to buy fresh vegetables.",
  "user": "She go to market buy fresh vegetable."
 },
 {
  "id": 3,
  "correct": "He doesn\u2019t like playing football in the rain.",
  "user": "He not like play football in rain."
 },
 {
  "id": 4,
  "correct": "We were watching a movie when the lights went out.",
  "user": "We watch movie when lights go out."
 },
 {
  "id": 5,
  "correct": "They have been studying English for two years.",
  "user": "They study English two year."
 }
]